{
    "url": "https://crautos.com/autosusados/cardetail.cfm?c=10301928&Hyundai.ACCENT.2013",
    "año": 2013,
    "marca": "HYUNDAI",
    "modelo": "ACCENT",
    "precio_crc": 10359,
    "precio_usd": 5200000.0,
    "imagen_principal": "https://crautos.com/clasificados/usados/10301928-1.jpg",
    "galeria_imagenes": [
        "https://crautos.com/clasificados/usados/10301928-1.jpg",
        "https://crautos.com/clasificados/usados/10301928-2.jpg",
        "https://crautos.com/clasificados/usados/10301928-3.jpg",
        "https://crautos.com/clasificados/usados/10301928-4.jpg",
        "https://crautos.com/clasificados/usados/10301928-5.jpg"
    ],
    "vendedor": {
        "nombre": "SERGIO ADOLFO MORUA MORA",
        "teléfono": "8731-2747 8781-3689",
        "whatsapp": "8731-2747"
    },
    "informacion_general": {
        "cilindrada": "1600 cc",
        "estilo": "Sedán",
        "#_de_pasajeros": "5",
        "combustible": "Gasolina",
        "transmisión": "Automática/Dual",
        "estado": "Excelente",
        "kilometraje": "100,000 millas",
        "placa": "Termina en 7",
        "color_exterior": "AZUL",
        "color_interior": "GRIS/NEGRO",
        "#_de_puertas": "4",
        "ya_pagó_impuestos": "SI",
        "precio_negociable": "SI",
        "se_recibe_vehículo": "NO",
        "provincia": "San José",
        "fecha_de_ingreso": "07 de Julio del 2025",
        "comentario_vendedor": "Carro de Familia muy cuidado.",
        "kilometraje_number": 100000,
        "cilindrada_number": 1600
    },
    "equipamiento": [
        "Aire acondicionado",
        "Bluetooth",
        "Bolsa de aire",
        "Caja de cambios dual",
        "Cierre central",
        "Control electrónico de estabilidad",
        "Cámara de retroceso",
        "Desempañador Trasero",
        "Dirección Hidráulica/Electroasistida",
        "Espejos eléctricos",
        "Frenos ABS",
        "Halógenos",
        "Radio con USB/AUX",
        "Revisión Técnica al día",
        "Vidrios eléctricos",
        "Vidrios tintados",
        "Volante ajustable"
    ],
    "antiguedad": 12
}