{
    "url": "https://crautos.com/autosusados/cardetail.cfm?c=25219138&Volkswagen.TIGUAN.2021",
    "año": 2021,
    "marca": "VOLKSWAGEN",
    "modelo": "TIGUAN",
    "precio_crc": 33865,
    "precio_usd": 17000000.0,
    "imagen_principal": "https://crautos.com/clasificados/usados/25219138-1.jpg",
    "galeria_imagenes": [
        "https://crautos.com/clasificados/usados/25219138-1.jpg",
        "https://crautos.com/clasificados/usados/25219138-2.jpg",
        "https://crautos.com/clasificados/usados/25219138-3.jpg",
        "https://crautos.com/clasificados/usados/25219138-4.jpg",
        "https://crautos.com/clasificados/usados/25219138-5.jpg"
    ],
    "vendedor": {
        "nombre": "ROY FALLAS",
        "teléfono": "6195-0231",
        "whatsapp": "6195-0231"
    },
    "informacion_general": {
        "cilindrada": "2000 cc",
        "estilo": "SUV 4WD/AWD",
        "#_de_pasajeros": "7",
        "combustible": "Gasolina",
        "transmisión": "Automática/Dual",
        "estado": "Excelente",
        "kilometraje": "39,430 kms",
        "placa": "Termina en 0",
        "color_exterior": "BLANCO",
        "color_interior": "NEGRO",
        "#_de_puertas": "5",
        "ya_pagó_impuestos": "SI",
        "precio_negociable": "SI",
        "se_recibe_vehículo": "NO",
        "provincia": "Heredia",
        "fecha_de_ingreso": "11 de Agosto del 2025",
        "comentario_vendedor": "FULL MANTENIMIENTO, EXCELENTES CONDICIONES.",
        "kilometraje_number": 39430,
        "cilindrada_number": 2000
    },
    "equipamiento": [
        "Aire acondicionado",
        "Aire acondicionado climatizado",
        "Alarma",
        "Android Auto",
        "Apple CarPlay",
        "Aros de lujo",
        "Asientos eléctricos",
        "Bluetooth",
        "Bolsa de aire",
        "Cierre central",
        "Control crucero",
        "Control de radio en el volante",
        "Control electrónico de estabilidad",
        "Cámara de retroceso",
        "Desempañador Trasero",
        "Dirección Hidráulica/Electroasistida",
        "Espejos eléctricos",
        "Frenos ABS",
        "Halógenos",
        "Llave inteligente/botón de arranque",
        "Radio con USB/AUX",
        "Revisión Técnica al día",
        "Sensores de retroceso",
        "Tapicería de cuero",
        "Vidrios eléctricos",
        "Vidrios tintados",
        "Volante ajustable",
        "Volante multifuncional"
    ],
    "antiguedad": 4
}