{
    "url": "https://crautos.com/autosusados/cardetail.cfm?c=27153907&Kia.SPORTAGE%20.2018",
    "año": 2018,
    "marca": "KIA",
    "modelo": "SPORTAGE",
    "precio_crc": 21414,
    "precio_usd": 10750000.0,
    "imagen_principal": "https://crautos.com/clasificados/usados/27153907-1.jpg",
    "galeria_imagenes": [
        "https://crautos.com/clasificados/usados/27153907-1.jpg",
        "https://crautos.com/clasificados/usados/27153907-2.jpg",
        "https://crautos.com/clasificados/usados/27153907-3.jpg",
        "https://crautos.com/clasificados/usados/27153907-4.jpg",
        "https://crautos.com/clasificados/usados/27153907-5.jpg"
    ],
    "vendedor": {
        "nombre": "MATHIUN ZAMORA RODRIGUEZ",
        "teléfono": "8760-0150 8708-4488",
        "whatsapp": "8760-0150"
    },
    "informacion_general": {
        "cilindrada": "2000 cc",
        "estilo": "SUV 4WD/AWD",
        "#_de_pasajeros": "5",
        "combustible": "Gasolina",
        "transmisión": "Automática/Dual",
        "estado": "Excelente",
        "kilometraje": "65,000 kms",
        "placa": "Termina en 5",
        "color_exterior": "BALNCO",
        "color_interior": "NEGRO",
        "#_de_puertas": "5",
        "ya_pagó_impuestos": "SI",
        "precio_negociable": "SI",
        "se_recibe_vehículo": "SI",
        "provincia": "Alajuela",
        "fecha_de_ingreso": "10 de Julio del 2025",
        "comentario_vendedor": "Carro en muy buenas condiciones de cochera se recibe Colorado Hylux Forntier se da vulto .",
        "kilometraje_number": 65000,
        "cilindrada_number": 2000
    },
    "equipamiento": [
        "Aire acondicionado",
        "Apple CarPlay",
        "Aros de lujo",
        "Bluetooth",
        "Bolsa de aire",
        "Caja de cambios dual",
        "Cierre central",
        "Control de descenso",
        "Control de radio en el volante",
        "Cámara de retroceso",
        "Desempañador Trasero",
        "Dirección Hidráulica/Electroasistida",
        "Frenos ABS",
        "Halógenos",
        "Revisión Técnica al día",
        "Vidrios eléctricos",
        "Vidrios tintados",
        "Volante ajustable",
        "Volante multifuncional"
    ],
    "antiguedad": 7
}