{
    "url": "https://crautos.com/autosusados/cardetail.cfm?c=30068697&Suzuki.VITARA%20GL%20PLUS%20Z.2021",
    "año": 2021,
    "marca": "SUZUKI",
    "modelo": "VITARA GL PLUS Z",
    "precio_crc": 20916,
    "precio_usd": 10500000.0,
    "imagen_principal": "https://crautos.com/clasificados/usados/30068697-1.jpg",
    "galeria_imagenes": [
        "https://crautos.com/clasificados/usados/30068697-1.jpg",
        "https://crautos.com/clasificados/usados/30068697-2.jpg",
        "https://crautos.com/clasificados/usados/30068697-3.jpg",
        "https://crautos.com/clasificados/usados/30068697-4.jpg",
        "https://crautos.com/clasificados/usados/30068697-5.jpg"
    ],
    "vendedor": {
        "nombre": "DAVIS SALAZAR",
        "teléfono": "8827-7109",
        "whatsapp": "8827-7109"
    },
    "informacion_general": {
        "cilindrada": "1600 cc",
        "estilo": "SUV 2WD",
        "#_de_pasajeros": "5",
        "combustible": "Gasolina",
        "transmisión": "Automática/Dual",
        "estado": "Excelente",
        "kilometraje": "80,100 kms",
        "placa": "Termina en 2",
        "color_exterior": "GRIS PLOMO",
        "color_interior": "NEGRO",
        "#_de_puertas": "5",
        "ya_pagó_impuestos": "SI",
        "precio_negociable": "SI",
        "se_recibe_vehículo": "NO",
        "provincia": "Alajuela",
        "fecha_de_ingreso": "24 de Julio del 2025",
        "comentario_vendedor": "Muy cuidado record agencia elegante y económica .",
        "kilometraje_number": 80100,
        "cilindrada_number": 1600
    },
    "equipamiento": [
        "Aire acondicionado",
        "Aire acondicionado climatizado",
        "Alarma",
        "Android Auto",
        "Apple CarPlay",
        "Aros de lujo",
        "Bluetooth",
        "Bolsa de aire",
        "Caja de cambios dual",
        "Cierre central",
        "Computadora de viaje",
        "Control crucero",
        "Control de descenso",
        "Control de radio en el volante",
        "Control electrónico de estabilidad",
        "Cámara 360",
        "Cámara de retroceso",
        "Desempañador Trasero",
        "Dirección Hidráulica/Electroasistida",
        "Espejos eléctricos",
        "Frenos ABS",
        "Halógenos",
        "Llave inteligente/botón de arranque",
        "Radio con USB/AUX",
        "Revisión Técnica al día",
        "Sensores de retroceso",
        "Vidrios eléctricos",
        "Vidrios tintados",
        "Volante ajustable",
        "Volante multifuncional"
    ],
    "antiguedad": 4
}