{
    "url": "https://crautos.com/autosusados/cardetail.cfm?c=5973609&BMW.X5%2035I%20XDRIVE.2015",
    "año": 2015,
    "marca": "BMW",
    "modelo": "X5 35I XDRIVE",
    "precio_crc": 27689,
    "precio_usd": 13900000.0,
    "imagen_principal": "https://crautos.com/clasificados/usados/5973609-1.jpg",
    "galeria_imagenes": [
        "https://crautos.com/clasificados/usados/5973609-1.jpg",
        "https://crautos.com/clasificados/usados/5973609-2.jpg",
        "https://crautos.com/clasificados/usados/5973609-3.jpg",
        "https://crautos.com/clasificados/usados/5973609-4.jpg",
        "https://crautos.com/clasificados/usados/5973609-5.jpg"
    ],
    "vendedor": {
        "nombre": "AUTO PLAZA",
        "teléfono": "2573-6060 8325-3875",
        "whatsapp": "8484-5959",
        "dirección": "400 mts Norte de la Bomba Delta, contiguo a la Guacamaya y La Dos Pinos La Lima Cartago"
    },
    "informacion_general": {
        "cilindrada": "3000 cc",
        "estilo": "SUV 4WD/AWD",
        "#_de_pasajeros": "5",
        "combustible": "Gasolina",
        "transmisión": "Automática/Dual",
        "estado": "Excelente",
        "kilometraje": "127,000 kms",
        "placa": "ND",
        "color_exterior": "NEGRO",
        "color_interior": "BLANCO",
        "#_de_puertas": "4",
        "ya_pagó_impuestos": "SI",
        "precio_negociable": "SI",
        "se_recibe_vehículo": "SI",
        "provincia": "Cartago",
        "fecha_de_ingreso": "18 de Febrero del 2025",
        "comentario_vendedor": "Recibimos, financiamos, RUNFLAT NUEVAS, audio Harman Kardon, techo panorámico, cuero real, cámara.",
        "kilometraje_number": 127000,
        "cilindrada_number": 3000
    },
    "equipamiento": [
        "Aire acondicionado",
        "Aire acondicionado climatizado",
        "Alarma",
        "Aros de lujo",
        "Asiento con memoria",
        "Asientos eléctricos",
        "Bluetooth",
        "Bolsa de aire",
        "Caja de cambios dual",
        "Cierre central",
        "Computadora de viaje",
        "Control crucero",
        "Control de descenso",
        "Control de radio en el volante",
        "Control electrónico de estabilidad",
        "Cámara de retroceso",
        "Desempañador Trasero",
        "Dirección Hidráulica/Electroasistida",
        "Espejos eléctricos",
        "Frenos ABS",
        "Halógenos",
        "Llave inteligente/botón de arranque",
        "Luces de Xenón/Bixenón",
        "Radio con USB/AUX",
        "Retrovisores auto-retractibles",
        "Revisión Técnica al día",
        "Sensor de lluvia",
        "Sensores de retroceso",
        "Sensores frontales",
        "Sunroof/techo panorámico",
        "Tapicería de cuero",
        "Turbo",
        "Vidrios eléctricos",
        "Vidrios tintados",
        "Volante ajustable",
        "Volante multifuncional"
    ],
    "antiguedad": 10
}