{
    "url": "https://crautos.com/autosusados/cardetail.cfm?c=64537517&Audi.Q2%20E-TRON.2021",
    "año": 2021,
    "marca": "AUDI",
    "modelo": "Q2 E-TRON",
    "precio_crc": 36255,
    "precio_usd": 18200000.0,
    "imagen_principal": "https://crautos.com/clasificados/usados/64537517-1.jpg",
    "galeria_imagenes": [
        "https://crautos.com/clasificados/usados/64537517-1.jpg",
        "https://crautos.com/clasificados/usados/64537517-2.jpg",
        "https://crautos.com/clasificados/usados/64537517-3.jpg",
        "https://crautos.com/clasificados/usados/64537517-4.jpg",
        "https://crautos.com/clasificados/usados/64537517-5.jpg",
        "https://crautos.com/clasificados/usados/64537517-6.jpg"
    ],
    "vendedor": {
        "nombre": "ARIEL ABARCA CAMACHO",
        "teléfono": "7012-9702 8602-0929"
    },
    "informacion_general": {
        "estilo": "SUV 4WD/AWD",
        "#_de_pasajeros": "5",
        "combustible": "Eléctrico",
        "autonomía": "275 kms",
        "batería": "39.0 kWh",
        "transmisión": "Manual",
        "estado": "Excelente",
        "kilometraje": "54,000 kms",
        "placa": "Termina en 0",
        "color_exterior": "BLANCO",
        "color_interior": "NEGRO",
        "#_de_puertas": "5",
        "ya_pagó_impuestos": "SI",
        "precio_negociable": "SI",
        "se_recibe_vehículo": "NO",
        "provincia": "Heredia",
        "fecha_de_ingreso": "07 de Julio del 2025",
        "comentario_vendedor": "Excelente estado, como nuevo, full extras, cuatro x cuatro, con cargador incluido.",
        "kilometraje_number": 54000
    },
    "equipamiento": [
        "Aire acondicionado",
        "Aire acondicionado climatizado",
        "Alarma",
        "Apple CarPlay",
        "Aros de lujo",
        "Bluetooth",
        "Bolsa de aire",
        "Caja de cambios dual",
        "Cierre central",
        "Control de descenso",
        "Control de radio en el volante",
        "Control electrónico de estabilidad",
        "Cámara de retroceso",
        "Desempañador Trasero",
        "Dirección Hidráulica/Electroasistida",
        "Espejos eléctricos",
        "Frenos ABS",
        "Halógenos",
        "Llave inteligente/botón de arranque",
        "Revisión Técnica al día",
        "Sensor de lluvia",
        "Sensores de retroceso",
        "Sensores frontales",
        "Sunroof/techo panorámico",
        "Tapicería de cuero",
        "Vidrios eléctricos",
        "Vidrios tintados",
        "Volante ajustable",
        "Volante multifuncional"
    ],
    "antiguedad": 4
}