{
    "url": "https://crautos.com/autosusados/cardetail.cfm?c=66236698&Volkswagen.CROSSFOX.2014",
    "año": 2014,
    "marca": "VOLKSWAGEN",
    "modelo": "CROSSFOX",
    "precio_crc": 10359,
    "precio_usd": 5200000.0,
    "imagen_principal": "https://crautos.com/clasificados/usados/66236698-1.jpg",
    "galeria_imagenes": [
        "https://crautos.com/clasificados/usados/66236698-1.jpg",
        "https://crautos.com/clasificados/usados/66236698-2.jpg",
        "https://crautos.com/clasificados/usados/66236698-3.jpg",
        "https://crautos.com/clasificados/usados/66236698-4.jpg",
        "https://crautos.com/clasificados/usados/66236698-5.jpg",
        "https://crautos.com/clasificados/usados/66236698-6.jpg",
        "https://crautos.com/clasificados/usados/66236698-7.jpg",
        "https://crautos.com/clasificados/usados/66236698-8.jpg"
    ],
    "vendedor": {
        "nombre": "DANIEL MOYA",
        "teléfono": "8991-8675 8391-0785",
        "whatsapp": "8991-8675"
    },
    "informacion_general": {
        "cilindrada": "1600 cc",
        "estilo": "SUV 2WD",
        "#_de_pasajeros": "5",
        "combustible": "Gasolina",
        "transmisión": "Manual",
        "estado": "Excelente",
        "kilometraje": "98,000 kms",
        "placa": "Termina en 5",
        "color_exterior": "BLANCO",
        "color_interior": "NEGRO",
        "#_de_puertas": "5",
        "ya_pagó_impuestos": "SI",
        "precio_negociable": "SI",
        "se_recibe_vehículo": "NO",
        "provincia": "San José",
        "fecha_de_ingreso": "15 de Agosto del 2025",
        "comentario_vendedor": "LLANTAS NUEVAS. REGISTRO DE MANTENIMIENTOS EN MECANICA TOTAL. . Atención, amantes de los SUV compactos. Pongo a su disposición un Volkswagen CROSSFOX 2014. Un vehículo ideal para la ciudad y la aventura. Su estilo SUV y capacidad para 5 pasajeros lo hacen versátil. Este ejemplar se encuentra en excelente estado. Su motor de 1600 cc a gasolina, con transmisión manual, garantiza un manejo ágil. El indicador de recorrido marca 98000 kilómetros. Dispone de frenos A B S y bolsa de aire para seguridad. Incluye alarma antirrobo, Bluetooth y cierre central. El volante multifuncional facilita la conducción. La revisión técnica está al día. El precio es negociable. Una oportunidad para tener un Volkswagen confiable.",
        "kilometraje_number": 98000,
        "cilindrada_number": 1600
    },
    "equipamiento": [
        "Aire acondicionado",
        "Alarma",
        "Aros de lujo",
        "Bluetooth",
        "Bolsa de aire",
        "Cierre central",
        "Computadora de viaje",
        "Control de radio en el volante",
        "Desempañador Trasero",
        "Dirección Hidráulica/Electroasistida",
        "Espejos eléctricos",
        "Frenos ABS",
        "Halógenos",
        "Radio con USB/AUX",
        "Revisión Técnica al día",
        "Vidrios eléctricos",
        "Vidrios tintados",
        "Volante ajustable",
        "Volante multifuncional"
    ],
    "antiguedad": 11
}