{
    "url": "https://crautos.com/autosusados/cardetail.cfm?c=75318451",
    "año": 2018,
    "marca": "NISSAN",
    "modelo": "FRONTIER ULTRALIMITED",
    "precio_crc": 35857,
    "precio_usd": 18000000.0,
    "imagen_principal": "https://crautos.com/clasificados/usados/75318451-1.jpg",
    "galeria_imagenes": [
        "https://crautos.com/clasificados/usados/75318451-1.jpg",
        "https://crautos.com/clasificados/usados/75318451-2.jpg",
        "https://crautos.com/clasificados/usados/75318451-3.jpg",
        "https://crautos.com/clasificados/usados/75318451-4.jpg",
        "https://crautos.com/clasificados/usados/75318451-5.jpg",
        "https://crautos.com/clasificados/usados/75318451-6.jpg"
    ],
    "vendedor": {
        "nombre": "ERICK CORRALES",
        "teléfono": "8829-2527 7065-8270",
        "whatsapp": "8829-2527"
    },
    "informacion_general": {
        "cilindrada": "2500 cc",
        "estilo": "Pick Up 4WD",
        "#_de_pasajeros": "5",
        "combustible": "Diesel",
        "transmisión": "Automática/Dual",
        "estado": "Excelente",
        "kilometraje": "109,000 kms",
        "placa": "Termina en 3",
        "color_exterior": "GRIS",
        "color_interior": "CUERO NEGRO",
        "#_de_puertas": "4",
        "ya_pagó_impuestos": "SI",
        "precio_negociable": "SI",
        "se_recibe_vehículo": "NO",
        "provincia": "San José",
        "fecha_de_ingreso": "31 de Julio del 2025",
        "comentario_vendedor": "Oportunidad! Un solo Dueño! Excelentes extras como lona dura con luz antifaces y llantas AT..",
        "kilometraje_number": 109000,
        "cilindrada_number": 2500
    },
    "equipamiento": [
        "Aire acondicionado",
        "Aire acondicionado climatizado",
        "Alarma",
        "Aros de lujo",
        "Asientos eléctricos",
        "Bluetooth",
        "Bolsa de aire",
        "Caja de cambios dual",
        "Cierre central",
        "Control de descenso",
        "Control de radio en el volante",
        "Control electrónico de estabilidad",
        "Cámara de retroceso",
        "Desempañador Trasero",
        "Dirección Hidráulica/Electroasistida",
        "Espejos eléctricos",
        "Frenos ABS",
        "Halógenos",
        "Llave inteligente/botón de arranque",
        "Radio con USB/AUX",
        "Retrovisores auto-retractibles",
        "Revisión Técnica al día",
        "Sensores de retroceso",
        "Tapicería de cuero",
        "Turbo",
        "Vidrios eléctricos",
        "Vidrios tintados",
        "Volante ajustable",
        "Volante multifuncional"
    ],
    "antiguedad": 7
}