{
    "url": "https://crautos.com/autosusados/cardetail.cfm?c=7880712&Land%20Rover.DISCOVERY%202.2004",
    "año": 2004,
    "marca": "LAND ROVER",
    "modelo": "DISCOVERY 2",
    "precio_crc": 8032000,
    "precio_usd": 16000.0,
    "imagen_principal": "https://crautos.com/clasificados/usados/7880712-1.jpg",
    "galeria_imagenes": [
        "https://crautos.com/clasificados/usados/7880712-1.jpg",
        "https://crautos.com/clasificados/usados/7880712-2.jpg",
        "https://crautos.com/clasificados/usados/7880712-3.jpg",
        "https://crautos.com/clasificados/usados/7880712-4.jpg",
        "https://crautos.com/clasificados/usados/7880712-5.jpg"
    ],
    "vendedor": {
        "nombre": "MOTOR CITY",
        "teléfono": "8844-1919 8364-5234 2100-0808",
        "whatsapp": "8844-1919",
        "dirección": "San Rafael de Escazú, 75 Mtrs sur del Centro Comercial Paco"
    },
    "informacion_general": {
        "cilindrada": "2500 cc",
        "estilo": "SUV 4WD/AWD",
        "#_de_pasajeros": "7",
        "combustible": "Diesel",
        "transmisión": "Automática/Dual",
        "estado": "Excelente",
        "kilometraje": "230,000 kms",
        "placa": "Termina en 4",
        "color_exterior": "AZUL",
        "color_interior": "BEIGE",
        "#_de_puertas": "5",
        "ya_pagó_impuestos": "SI",
        "precio_negociable": "SI",
        "se_recibe_vehículo": "SI",
        "provincia": "San José",
        "fecha_de_ingreso": "05 de Agosto del 2025",
        "comentario_vendedor": "Turbo de geometría variable nuevo, Pintura nueva, suspensión trasera nueva, Tapicería y llantas nuev.",
        "kilometraje_number": 230000,
        "cilindrada_number": 2500
    },
    "equipamiento": [
        "Aire acondicionado",
        "Alarma",
        "Aros de lujo",
        "Bluetooth",
        "Bolsa de aire",
        "Caja de cambios dual",
        "Cierre central",
        "Control crucero",
        "Control de descenso",
        "Control electrónico de estabilidad",
        "Desempañador Trasero",
        "Dirección Hidráulica/Electroasistida",
        "Espejos eléctricos",
        "Frenos ABS",
        "Halógenos",
        "Radio con USB/AUX",
        "Revisión Técnica al día",
        "Tapicería de cuero",
        "Turbo",
        "Vidrios eléctricos",
        "Vidrios tintados",
        "Volante ajustable"
    ],
    "antiguedad": 21
}