{
    "url": "https://crautos.com/autosusados/cardetail.cfm?c=94127316&Toyota.COROLLA.2017",
    "año": 2017,
    "marca": "TOYOTA",
    "modelo": "COROLLA",
    "precio_crc": 16335,
    "precio_usd": 8200000.0,
    "imagen_principal": null,
    "galeria_imagenes": [
        "images/nopiclg.jpg"
    ],
    "vendedor": {
        "nombre": "JESSICA MÉNDEZ",
        "teléfono": "8624-3694",
        "whatsapp": "8624-3694"
    },
    "informacion_general": {
        "cilindrada": "1800 cc",
        "estilo": "Sedán",
        "#_de_pasajeros": "5",
        "combustible": "Gasolina",
        "transmisión": "Automática/Dual",
        "estado": "Excelente",
        "kilometraje": "69,000 millas",
        "placa": "Termina en 3",
        "color_exterior": "GRIS",
        "color_interior": "GRIS",
        "#_de_puertas": "4",
        "ya_pagó_impuestos": "SI",
        "precio_negociable": "SI",
        "se_recibe_vehículo": "NO",
        "provincia": "Alajuela",
        "fecha_de_ingreso": "12 de Agosto del 2025",
        "comentario_vendedor": "Excelente estado. Ya el vehículo está inscrito.",
        "kilometraje_number": 69000,
        "cilindrada_number": 1800
    },
    "equipamiento": [
        "Aire acondicionado",
        "Alarma",
        "Bluetooth",
        "Bolsa de aire",
        "Cierre central",
        "Computadora de viaje",
        "Control crucero",
        "Control de descenso",
        "Control de radio en el volante",
        "Cámara de retroceso",
        "Dirección Hidráulica/Electroasistida",
        "Frenos ABS",
        "Radio con USB/AUX",
        "Retrovisores auto-retractibles",
        "Revisión Técnica al día",
        "Vidrios eléctricos",
        "Volante ajustable",
        "Volante multifuncional"
    ],
    "antiguedad": 8
}