{
    "url": "https://crautos.com/autosusados/cardetail.cfm?c=9954100&Audi.Q5%20QUATTRO.2017",
    "año": 2017,
    "marca": "AUDI",
    "modelo": "Q5 QUATTRO",
    "precio_crc": 9939600,
    "precio_usd": 19800.0,
    "imagen_principal": "https://crautos.com/clasificados/usados/9954100-1.jpg",
    "galeria_imagenes": [
        "https://crautos.com/clasificados/usados/9954100-1.jpg",
        "https://crautos.com/clasificados/usados/9954100-2.jpg",
        "https://crautos.com/clasificados/usados/9954100-3.jpg",
        "https://crautos.com/clasificados/usados/9954100-4.jpg"
    ],
    "vendedor": {
        "nombre": "MOTOR CITY",
        "teléfono": "8844-1919 8364-5234 2100-0808",
        "whatsapp": "8844-1919",
        "dirección": "San Rafael de Escazú, 75 Mtrs sur del Centro Comercial Paco"
    },
    "informacion_general": {
        "cilindrada": "2000 cc",
        "estilo": "SUV 4WD/AWD",
        "#_de_pasajeros": "5",
        "combustible": "Gasolina",
        "transmisión": "Automática/Dual",
        "estado": "Excelente",
        "kilometraje": "103,000 kms",
        "placa": "Termina en 4",
        "color_exterior": "NEGRO",
        "color_interior": "CAFE",
        "#_de_puertas": "5",
        "ya_pagó_impuestos": "SI",
        "precio_negociable": "SI",
        "se_recibe_vehículo": "SI",
        "provincia": "San José",
        "fecha_de_ingreso": "21 de Julio del 2025",
        "comentario_vendedor": "EXCELENTE ESTADO, TAPICERIA EN BUEN ESTADO, MEJOR PRECIO DEL MERCADO.",
        "kilometraje_number": 103000,
        "cilindrada_number": 2000
    },
    "equipamiento": [
        "Aire acondicionado",
        "Alarma",
        "Aros de lujo",
        "Bluetooth",
        "Bolsa de aire",
        "Caja de cambios dual",
        "Cierre central",
        "Computadora de viaje",
        "Control de radio en el volante",
        "Control electrónico de estabilidad",
        "Desempañador Trasero",
        "Dirección Hidráulica/Electroasistida",
        "Espejos eléctricos",
        "Frenos ABS",
        "Halógenos",
        "Llave inteligente/botón de arranque",
        "Revisión Técnica al día",
        "Tapicería de cuero",
        "Turbo",
        "Vidrios eléctricos",
        "Vidrios tintados",
        "Volante ajustable"
    ],
    "antiguedad": 8
}