{
    "url": "https://crautos.com/autosusados/cardetail.cfm?c=19920624&Chevrolet.CAMARO%20SS.2018",
    "año": 2018,
    "marca": "CHEVROLET",
    "modelo": "CAMARO SS",
    "precio_crc": 48207,
    "precio_usd": 24200000.0,
    "imagen_principal": "https://crautos.com/clasificados/usados/19920624-1.jpg",
    "galeria_imagenes": [
        "https://crautos.com/clasificados/usados/19920624-1.jpg",
        "https://crautos.com/clasificados/usados/19920624-2.jpg",
        "https://crautos.com/clasificados/usados/19920624-3.jpg",
        "https://crautos.com/clasificados/usados/19920624-4.jpg",
        "https://crautos.com/clasificados/usados/19920624-5.jpg"
    ],
    "vendedor": {
        "nombre": "GERARDO",
        "teléfono": "8306-9303",
        "whatsapp": "8306-9303"
    },
    "informacion_general": {
        "cilindrada": "6200 cc",
        "estilo": "Sedán",
        "#_de_pasajeros": "4",
        "combustible": "Gasolina",
        "transmisión": "Automática/Dual",
        "estado": "Excelente",
        "kilometraje": "11,000 kms",
        "placa": "Termina en 5",
        "color_exterior": "ROJO",
        "color_interior": "NEGRO",
        "#_de_puertas": "2",
        "ya_pagó_impuestos": "SI",
        "precio_negociable": "SI",
        "se_recibe_vehículo": "NO",
        "provincia": "San José",
        "fecha_de_ingreso": "30 de Julio del 2025",
        "comentario_vendedor": "Camaro SS Único dueño como nuevo Tratami cerámico Head Up display..",
        "kilometraje_number": 11000,
        "cilindrada_number": 6200
    },
    "equipamiento": [
        "Aire acondicionado",
        "Aire acondicionado climatizado",
        "Alarma",
        "Apple CarPlay",
        "Aros de lujo",
        "Asiento con memoria",
        "Asientos eléctricos",
        "Bluetooth",
        "Bolsa de aire",
        "Caja de cambios dual",
        "Cierre central",
        "Computadora de viaje",
        "Control crucero",
        "Control de descenso",
        "Control de radio en el volante",
        "Control electrónico de estabilidad",
        "Cámara de retroceso",
        "Desempañador Trasero",
        "Dirección Hidráulica/Electroasistida",
        "Espejos eléctricos",
        "Frenos ABS",
        "Halógenos",
        "Llave inteligente/botón de arranque",
        "Luces de Xenón/Bixenón",
        "Radio con USB/AUX",
        "Retrovisores auto-retractibles",
        "Revisión Técnica al día",
        "Sensor de lluvia",
        "Sensores de retroceso",
        "Sensores frontales",
        "Sunroof/techo panorámico",
        "Tapicería de cuero",
        "Turbo",
        "Vidrios eléctricos",
        "Vidrios tintados",
        "Volante ajustable",
        "Volante multifuncional"
    ],
    "antiguedad": 7
}