{
    "url": "https://crautos.com/autosusados/cardetail.cfm?c=36419941",
    "año": 2023,
    "marca": "NISSAN",
    "modelo": "KICKS",
    "precio_crc": 22000,
    "precio_usd": 11044000.0,
    "imagen_principal": "https://crautos.com/clasificados/usados/36419941-1.jpg",
    "galeria_imagenes": [
        "https://crautos.com/clasificados/usados/36419941-1.jpg",
        "https://crautos.com/clasificados/usados/36419941-2.jpg",
        "https://crautos.com/clasificados/usados/36419941-3.jpg",
        "https://crautos.com/clasificados/usados/36419941-4.jpg",
        "https://crautos.com/clasificados/usados/36419941-5.jpg",
        "https://crautos.com/clasificados/usados/36419941-6.jpg",
        "https://crautos.com/clasificados/usados/36419941-7.jpg"
    ],
    "vendedor": {
        "nombre": "MIKE LANG",
        "teléfono": "8384-1218",
        "whatsapp": "8384-1218"
    },
    "informacion_general": {
        "cilindrada": "1600 cc",
        "estilo": "SUV 2WD",
        "#_de_pasajeros": "5",
        "combustible": "Gasolina",
        "transmisión": "Automática/Dual",
        "estado": "Excelente",
        "kilometraje": "33,000 kms",
        "placa": "Termina en 8",
        "color_exterior": "BLANCO",
        "color_interior": "NEGRO",
        "#_de_puertas": "4",
        "ya_pagó_impuestos": "SI",
        "precio_negociable": "SI",
        "se_recibe_vehículo": "NO",
        "provincia": "San José",
        "fecha_de_ingreso": "14 de Julio del 2025",
        "comentario_vendedor": "EXCELENTE ESTADO - DOS MESES DE GARANTIA - POSIBLE FINANCIAMIENTO.",
        "kilometraje_number": 33000,
        "cilindrada_number": 1600
    },
    "equipamiento": [
        "Aire acondicionado",
        "Aire acondicionado climatizado",
        "Alarma",
        "Bluetooth",
        "Bolsa de aire",
        "Cierre central",
        "Control crucero",
        "Control de descenso",
        "Control de radio en el volante",
        "Control electrónico de estabilidad",
        "Cámara de retroceso",
        "Desempañador Trasero",
        "Dirección Hidráulica/Electroasistida",
        "Espejos eléctricos",
        "Frenos ABS",
        "Llave inteligente/botón de arranque",
        "Radio con USB/AUX",
        "Revisión Técnica al día",
        "Sensores de retroceso",
        "Vidrios eléctricos",
        "Vidrios tintados",
        "Volante multifuncional"
    ],
    "antiguedad": 2
}