{
    "url": "https://crautos.com/autosusados/cardetail.cfm?c=4365901&Jeep.WRANGLER%20SAHARA%20UNLIMITED.2021",
    "año": 2021,
    "marca": "JEEP",
    "modelo": "WRANGLER SAHARA UNLIMITED",
    "precio_crc": 30120000,
    "precio_usd": 60000.0,
    "imagen_principal": "https://crautos.com/clasificados/usados/4365901-1.jpg",
    "galeria_imagenes": [
        "https://crautos.com/clasificados/usados/4365901-1.jpg",
        "https://crautos.com/clasificados/usados/4365901-2.jpg",
        "https://crautos.com/clasificados/usados/4365901-3.jpg",
        "https://crautos.com/clasificados/usados/4365901-4.jpg",
        "https://crautos.com/clasificados/usados/4365901-5.jpg"
    ],
    "vendedor": {
        "nombre": "MOACYR Z MOTORS",
        "teléfono": "6040-3050 6195-4459 6421-1381",
        "whatsapp": "6040-3050",
        "dirección": "Santo Domingo, de la Basílica 200 mts Norte y 200 mts Este / San Francisco, detrás de Wal-Mart. Contiguo Gasolinera NASA"
    },
    "informacion_general": {
        "cilindrada": "3600 cc",
        "estilo": "SUV 4WD/AWD",
        "#_de_pasajeros": "5",
        "combustible": "Gasolina",
        "transmisión": "Automática/Dual",
        "estado": "Excelente",
        "kilometraje": "45,500 kms",
        "placa": "Termina en 3",
        "color_exterior": "AMARILLO",
        "color_interior": "CUERO REAL",
        "#_de_puertas": "4",
        "ya_pagó_impuestos": "SI",
        "precio_negociable": "NO",
        "se_recibe_vehículo": "SI",
        "provincia": "Heredia",
        "fecha_de_ingreso": "09 de Junio del 2025",
        "comentario_vendedor": "ENGLISH SPOKEN, IG: ZMOTORSCR FB: Z MOTORS. Contáctenos x WhatsApp..",
        "kilometraje_number": 45500,
        "cilindrada_number": 3600
    },
    "equipamiento": [
        "Aire acondicionado",
        "Apple CarPlay",
        "Aros de lujo",
        "Bluetooth",
        "Bolsa de aire",
        "Caja de cambios dual",
        "Cierre central",
        "Computadora de viaje",
        "Control de descenso",
        "Control de radio en el volante",
        "Control electrónico de estabilidad",
        "Cámara de retroceso",
        "Dirección Hidráulica/Electroasistida",
        "Espejos eléctricos",
        "Frenos ABS",
        "Halógenos",
        "Llave inteligente/botón de arranque",
        "Luces de Xenón/Bixenón",
        "Radio con USB/AUX",
        "Revisión Técnica al día",
        "Sensor de lluvia",
        "Sensores de retroceso",
        "Sunroof/techo panorámico",
        "Tapicería de cuero",
        "Vidrios eléctricos",
        "Vidrios tintados",
        "Volante ajustable",
        "Volante multifuncional"
    ],
    "antiguedad": 4
}