{
    "url": "https://crautos.com/autosusados/cardetail.cfm?c=44293502&Hyundai.TERRACAN.2001",
    "año": 2001,
    "marca": "HYUNDAI",
    "modelo": "TERRACAN",
    "precio_crc": 9562,
    "precio_usd": 4800000.0,
    "imagen_principal": "https://crautos.com/clasificados/usados/44293502-1.jpg",
    "galeria_imagenes": [
        "https://crautos.com/clasificados/usados/44293502-1.jpg",
        "https://crautos.com/clasificados/usados/44293502-2.jpg",
        "https://crautos.com/clasificados/usados/44293502-3.jpg",
        "https://crautos.com/clasificados/usados/44293502-4.jpg",
        "https://crautos.com/clasificados/usados/44293502-5.jpg"
    ],
    "vendedor": {
        "nombre": "EDUARDO WRAY",
        "teléfono": "8348-9944 7016-9870",
        "whatsapp": "8348-9944"
    },
    "informacion_general": {
        "cilindrada": "2500 cc",
        "estilo": "SUV 4WD/AWD",
        "#_de_pasajeros": "7",
        "combustible": "Diesel",
        "transmisión": "Manual",
        "estado": "Excelente",
        "kilometraje": "235,000 kms",
        "placa": "Termina en 0",
        "color_exterior": "BLANCO",
        "color_interior": "GRIS",
        "#_de_puertas": "5",
        "ya_pagó_impuestos": "SI",
        "precio_negociable": "SI",
        "se_recibe_vehículo": "SI",
        "provincia": "Alajuela",
        "fecha_de_ingreso": "08 de Agosto del 2025",
        "comentario_vendedor": "Tapicería de Cuero. Llantas como nuevas. Pantalla Android. Se recibe. Financiamiento disponible.",
        "kilometraje_number": 235000,
        "cilindrada_number": 2500
    },
    "equipamiento": [
        "Aire acondicionado",
        "Alarma",
        "Android Auto",
        "Aros de lujo",
        "Bluetooth",
        "Bolsa de aire",
        "Cierre central",
        "Control crucero",
        "Dirección Hidráulica/Electroasistida",
        "Espejos eléctricos",
        "Frenos ABS",
        "Halógenos",
        "Radio con USB/AUX",
        "Retrovisores auto-retractibles",
        "Revisión Técnica al día",
        "Sensores de retroceso",
        "Tapicería de cuero",
        "Turbo",
        "Vidrios eléctricos",
        "Vidrios tintados",
        "Volante ajustable"
    ],
    "antiguedad": 24
}