{
    "url": "https://crautos.com/autosusados/cardetail.cfm?c=70564264&Mitsubishi.L200.2012",
    "año": 2012,
    "marca": "MITSUBISHI",
    "modelo": "L200",
    "precio_crc": 23506,
    "precio_usd": 11800000.0,
    "imagen_principal": "https://crautos.com/clasificados/usados/70564264-1.jpg",
    "galeria_imagenes": [
        "https://crautos.com/clasificados/usados/70564264-1.jpg",
        "https://crautos.com/clasificados/usados/70564264-2.jpg",
        "https://crautos.com/clasificados/usados/70564264-3.jpg"
    ],
    "vendedor": {
        "nombre": "VERONICA QUIROS",
        "teléfono": "8980-6401 8972-7667",
        "whatsapp": "8980-6401"
    },
    "informacion_general": {
        "cilindrada": "2500 cc",
        "estilo": "Pick Up 4WD",
        "#_de_pasajeros": "5",
        "combustible": "Gasolina",
        "transmisión": "Automática/Dual",
        "estado": "Muy Bueno",
        "kilometraje": "225,000 kms",
        "placa": "Termina en 2",
        "color_exterior": "GRIS",
        "color_interior": "NEGRO",
        "#_de_puertas": "5",
        "ya_pagó_impuestos": "SI",
        "precio_negociable": "SI",
        "se_recibe_vehículo": "SI",
        "provincia": "Cartago",
        "fecha_de_ingreso": "29 de Julio del 2025",
        "comentario_vendedor": "SE RECIBE .",
        "kilometraje_number": 225000,
        "cilindrada_number": 2500
    },
    "equipamiento": [],
    "antiguedad": 13
}