{
    "url": "https://crautos.com/autosusados/cardetail.cfm?c=70983088&Suzuki.GRAND%20VITARA%20.2016",
    "año": 2016,
    "marca": "SUZUKI",
    "modelo": "GRAND VITARA",
    "precio_crc": 15139,
    "precio_usd": 7600000.0,
    "imagen_principal": "https://crautos.com/clasificados/usados/70983088-1.jpg",
    "galeria_imagenes": [
        "https://crautos.com/clasificados/usados/70983088-1.jpg",
        "https://crautos.com/clasificados/usados/70983088-2.jpg",
        "https://crautos.com/clasificados/usados/70983088-3.jpg",
        "https://crautos.com/clasificados/usados/70983088-4.jpg",
        "https://crautos.com/clasificados/usados/70983088-5.jpg"
    ],
    "vendedor": {
        "nombre": "KEVIN ARAYA SOLORZANO",
        "teléfono": "6245-5444"
    },
    "informacion_general": {
        "cilindrada": "2400 cc",
        "estilo": "SUV 2WD",
        "#_de_pasajeros": "5",
        "combustible": "Gasolina",
        "transmisión": "Manual",
        "estado": "Excelente",
        "kilometraje": "100,000 kms",
        "placa": "Termina en 8",
        "color_exterior": "NEGRO",
        "color_interior": "GRIS PLATA",
        "#_de_puertas": "5",
        "ya_pagó_impuestos": "SI",
        "precio_negociable": "SI",
        "se_recibe_vehículo": "SI",
        "provincia": "Alajuela",
        "fecha_de_ingreso": "12 de Agosto del 2025",
        "comentario_vendedor": "Excelente estado .",
        "kilometraje_number": 100000,
        "cilindrada_number": 2400
    },
    "equipamiento": [
        "Aire acondicionado",
        "Aire acondicionado climatizado",
        "Alarma",
        "Android Auto",
        "Apple CarPlay",
        "Aros de lujo",
        "Bluetooth",
        "Bolsa de aire",
        "Cierre central",
        "Computadora de viaje",
        "Control de radio en el volante",
        "Cámara de retroceso",
        "Desempañador Trasero",
        "Dirección Hidráulica/Electroasistida",
        "Espejos eléctricos",
        "Frenos ABS",
        "Halógenos",
        "Luces de Xenón/Bixenón",
        "Radio con USB/AUX",
        "Revisión Técnica al día",
        "Vidrios eléctricos",
        "Vidrios tintados",
        "Volante ajustable",
        "Volante multifuncional"
    ],
    "antiguedad": 9
}