{
    "url": "https://crautos.com/autosusados/cardetail.cfm?c=88305168&Suzuki.JIMNY%20.2023",
    "año": 2023,
    "marca": "SUZUKI",
    "modelo": "JIMNY",
    "precio_crc": 25400,
    "precio_usd": 12750800.0,
    "imagen_principal": "https://crautos.com/clasificados/usados/88305168-1.jpg",
    "galeria_imagenes": [
        "https://crautos.com/clasificados/usados/88305168-1.jpg",
        "https://crautos.com/clasificados/usados/88305168-2.jpg",
        "https://crautos.com/clasificados/usados/88305168-3.jpg",
        "https://crautos.com/clasificados/usados/88305168-4.jpg"
    ],
    "vendedor": {
        "nombre": "MARCO",
        "teléfono": "6040-0565",
        "whatsapp": "6040-0565"
    },
    "informacion_general": {
        "cilindrada": "1500 cc",
        "estilo": "SUV 4WD/AWD",
        "#_de_pasajeros": "4",
        "combustible": "Gasolina",
        "transmisión": "Manual",
        "estado": "Excelente",
        "kilometraje": "9,980 kms",
        "placa": "Termina en 3",
        "color_exterior": "ARENA",
        "color_interior": "NEGRO",
        "#_de_puertas": "2",
        "ya_pagó_impuestos": "SI",
        "precio_negociable": "NO",
        "se_recibe_vehículo": "NO",
        "provincia": "Guanacaste",
        "fecha_de_ingreso": "08 de Agosto del 2025",
        "comentario_vendedor": "MUCHAS EXTRAS, CARRO DE COCHERA, SE VENDE PORQUE SE USA MUY POCO. IMPECABLE, COMO NUEVO..",
        "kilometraje_number": 9980,
        "cilindrada_number": 1500
    },
    "equipamiento": [
        "Aire acondicionado",
        "Android Auto",
        "Aros de lujo",
        "Bluetooth",
        "Bolsa de aire",
        "Cierre central",
        "Control de descenso",
        "Control de radio en el volante",
        "Control electrónico de estabilidad",
        "Cámara de retroceso",
        "Desempañador Trasero",
        "Dirección Hidráulica/Electroasistida",
        "Espejos eléctricos",
        "Frenos ABS",
        "Halógenos",
        "Radio con USB/AUX",
        "Revisión Técnica al día",
        "Vidrios eléctricos",
        "Vidrios tintados",
        "Volante ajustable",
        "Volante multifuncional"
    ],
    "antiguedad": 2
}